{
  "info": {
    "_postman_id": "cffd84d1-9b6e-4dba-9963-b20a4cee2846",
    "name": "Online Shop API",
    "schema": "https://schema.getpostman.com/json/collection/v2.1.0/collection.json",
    "_exporter_id": "53589592",
    "_collection_link": "https://go.postman.co/collection/53589592-cffd84d1-9b6e-4dba-9963-b20a4cee2846?source=collection_link"
  },
  "item": [
    {
      "name": "Categories",
      "item": [
        {
          "name": "Get All Categories",
          "request": {
            "method": "GET",
            "header": [],
            "url": {
              "raw": "http://127.0.0.1:8000/api/categories/",
              "protocol": "http",
              "host": [
                "127",
                "0",
                "0",
                "1"
              ],
              "port": "8000",
              "path": [
                "api",
                "categories",
                ""
              ]
            }
          },
          "response": []
        },
        {
          "name": "Get Category by ID",
          "request": {
            "method": "GET",
            "header": [],
            "url": {
              "raw": "http://127.0.0.1:8000/api/categories/1",
              "protocol": "http",
              "host": [
                "127",
                "0",
                "0",
                "1"
              ],
              "port": "8000",
              "path": [
                "api",
                "categories",
                "1"
              ]
            }
          },
          "response": []
        },
        {
          "name": "Get Products by Category",
          "request": {
            "method": "GET",
            "header": [],
            "url": {
              "raw": "http://127.0.0.1:8000/api/categories/1/products",
              "protocol": "http",
              "host": [
                "127",
                "0",
                "0",
                "1"
              ],
              "port": "8000",
              "path": [
                "api",
                "categories",
                "1",
                "products"
              ]
            }
          },
          "response": []
        },
        {
          "name": "Create Category",
          "request": {
            "method": "POST",
            "header": [],
            "body": {
              "mode": "raw",
              "raw": "{\n    \"name\": \"New Category\"\n}",
              "options": {
                "raw": {
                  "language": "json"
                }
              }
            },
            "url": {
              "raw": "http://127.0.0.1:8000/api/categories/",
              "protocol": "http",
              "host": [
                "127",
                "0",
                "0",
                "1"
              ],
              "port": "8000",
              "path": [
                "api",
                "categories",
                ""
              ]
            }
          },
          "response": []
        },
        {
          "name": "Update Category",
          "request": {
            "method": "PUT",
            "header": [],
            "body": {
              "mode": "raw",
              "raw": "{\n    \"name\": \"Update New Category name\"\n}",
              "options": {
                "raw": {
                  "language": "json"
                }
              }
            },
            "url": {
              "raw": "http://127.0.0.1:8000/api/categories/5/",
              "protocol": "http",
              "host": [
                "127",
                "0",
                "0",
                "1"
              ],
              "port": "8000",
              "path": [
                "api",
                "categories",
                "5",
                ""
              ]
            }
          },
          "response": []
        },
        {
          "name": "Delete Category",
          "request": {
            "method": "DELETE",
            "header": [],
            "url": {
              "raw": "http://127.0.0.1:8000/api/categories/5/",
              "protocol": "http",
              "host": [
                "127",
                "0",
                "0",
                "1"
              ],
              "port": "8000",
              "path": [
                "api",
                "categories",
                "5",
                ""
              ]
            }
          },
          "response": []
        }
      ]
    },
    {
      "name": "Products",
      "item": [
        {
          "name": "Get All Products",
          "request": {
            "method": "GET",
            "header": [],
            "url": {
              "raw": "http://127.0.0.1:8000/api/products/",
              "protocol": "http",
              "host": [
                "127",
                "0",
                "0",
                "1"
              ],
              "port": "8000",
              "path": [
                "api",
                "products",
                ""
              ]
            }
          },
          "response": []
        },
        {
          "name": "Get Product by ID",
          "request": {
            "method": "GET",
            "header": [],
            "url": {
              "raw": "http://127.0.0.1:8000/api/products/1/",
              "protocol": "http",
              "host": [
                "127",
                "0",
                "0",
                "1"
              ],
              "port": "8000",
              "path": [
                "api",
                "products",
                "1",
                ""
              ]
            }
          },
          "response": []
        },
        {
          "name": "Create Product",
          "request": {
            "method": "POST",
            "header": [],
            "body": {
              "mode": "raw",
              "raw": "{\n  \"name\": \"The Witcher 3\",\n  \"price\": \"39.99\",\n  \"description\": \"Popular RPG game\",\n  \"count\": 15,\n  \"is_active\": true,\n  \"category\": 3\n}",
              "options": {
                "raw": {
                  "language": "json"
                }
              }
            },
            "url": {
              "raw": "http://127.0.0.1:8000/api/products/",
              "protocol": "http",
              "host": [
                "127",
                "0",
                "0",
                "1"
              ],
              "port": "8000",
              "path": [
                "api",
                "products",
                ""
              ]
            }
          },
          "response": []
        },
        {
          "name": "Update Product",
          "request": {
            "method": "PUT",
            "header": [],
            "body": {
              "mode": "raw",
              "raw": "{\n    \"name\": \"The Witcher 3: Next Gen\",\n    \"price\": 69.9,\n    \"description\": \"Popular RPG game\",\n    \"count\": 15,\n    \"is_active\": true,\n    \"category\": 3\n}",
              "options": {
                "raw": {
                  "language": "json"
                }
              }
            },
            "url": {
              "raw": "http://127.0.0.1:8000/api/products/21/",
              "protocol": "http",
              "host": [
                "127",
                "0",
                "0",
                "1"
              ],
              "port": "8000",
              "path": [
                "api",
                "products",
                "21",
                ""
              ]
            }
          },
          "response": []
        },
        {
          "name": "Delete Product",
          "request": {
            "method": "DELETE",
            "header": [],
            "url": {
              "raw": "http://127.0.0.1:8000/api/products/21/",
              "protocol": "http",
              "host": [
                "127",
                "0",
                "0",
                "1"
              ],
              "port": "8000",
              "path": [
                "api",
                "products",
                "21",
                ""
              ]
            }
          },
          "response": []
        }
      ]
    }
  ]
}